odoo/addons/pos_receipt_hide_price/README.rst
odoo/addons/pos_receipt_hide_price/__init__.py
odoo/addons/pos_receipt_hide_price/__manifest__.py
odoo/addons/pos_receipt_hide_price/i18n/es.po
odoo/addons/pos_receipt_hide_price/i18n/it.po
odoo/addons/pos_receipt_hide_price/i18n/pos_receipt_hide_price.pot
odoo/addons/pos_receipt_hide_price/readme/CONTRIBUTORS.rst
odoo/addons/pos_receipt_hide_price/readme/DESCRIPTION.rst
odoo/addons/pos_receipt_hide_price/readme/USAGE.rst
odoo/addons/pos_receipt_hide_price/static/description/icon.png
odoo/addons/pos_receipt_hide_price/static/description/index.html
odoo/addons/pos_receipt_hide_price/static/description/price-hidden.png
odoo/addons/pos_receipt_hide_price/static/description/price-shown.png
odoo/addons/pos_receipt_hide_price/static/src/js/OrderReceipt.js
odoo/addons/pos_receipt_hide_price/static/src/js/ReceiptScreen.js
odoo/addons/pos_receipt_hide_price/static/src/js/ReprintReceiptScreen.js
odoo/addons/pos_receipt_hide_price/static/src/xml/HidePrice.xml
odoo/addons/pos_receipt_hide_price/static/src/xml/OrderReceipt.xml
odoo/addons/pos_receipt_hide_price/static/src/xml/ReceiptScreen.xml
odoo/addons/pos_receipt_hide_price/static/src/xml/ReprintReceiptScreen.xml
odoo_addon_pos_receipt_hide_price-16.0.1.0.0.7.dist-info/METADATA
odoo_addon_pos_receipt_hide_price-16.0.1.0.0.7.dist-info/WHEEL
odoo_addon_pos_receipt_hide_price-16.0.1.0.0.7.dist-info/top_level.txt
odoo_addon_pos_receipt_hide_price-16.0.1.0.0.7.dist-info/RECORD
